admin_sort/__init__.py
admin_sort/models.py
admin_sort/admin/__init__.py
admin_sort/admin/change_list.py
admin_sort/admin/inlines.py
admin_sort/locale/de/LC_MESSAGES/django.mo
admin_sort/locale/de/LC_MESSAGES/django.po
admin_sort/locale/en/LC_MESSAGES/django.mo
admin_sort/locale/en/LC_MESSAGES/django.po
admin_sort/locale/ru/LC_MESSAGES/django.mo
admin_sort/locale/ru/LC_MESSAGES/django.po
admin_sort/locale/uk/LC_MESSAGES/django.mo
admin_sort/locale/uk/LC_MESSAGES/django.po
admin_sort/static/admin_sort/sort.css
admin_sort/static/admin_sort/sort.js
admin_sort/static/admin_sort/sort.js.LICENSE.txt
admin_sort/templates/admin/admin_sort/change_list.html
admin_sort/templates/admin/admin_sort/edit_inline/inline.html
admin_sort/tests/__init__.py
admin_sort/tests/settings.py
admin_sort/tests/settings_admin_style.py
admin_sort/tests/settings_no_headless.py
admin_sort/tests/test_sortable_api.py
admin_sort/tests/test_sortable_selenium.py
admin_sort/tests/devapp/__init__.py
admin_sort/tests/devapp/admin.py
admin_sort/tests/devapp/models.py
admin_sort/tests/devapp/migrations/0001_initial.py
admin_sort/tests/devapp/migrations/__init__.py
admin_sort/tests/testapp/__init__.py
admin_sort/tests/testapp/admin.py
admin_sort/tests/testapp/models.py
admin_sort/tests/testapp/urls.py
admin_sort/tests/testapp/migrations/0001_initial.py
admin_sort/tests/testapp/migrations/0002_auto_20181104_0804.py
admin_sort/tests/testapp/migrations/__init__.py
admin_sort/tests/utils/__init__.py
admin_sort/tests/utils/django_utils.py
admin_sort/tests/utils/selenium_utils.py
admin_sort/utils/__init__.py
admin_sort/utils/model_sorting.py
django_admin_sort-0.4.0.dist-info/LICENCES
django_admin_sort-0.4.0.dist-info/METADATA
django_admin_sort-0.4.0.dist-info/WHEEL
django_admin_sort-0.4.0.dist-info/top_level.txt
django_admin_sort-0.4.0.dist-info/RECORD
