Metadata-Version: 2.1
Name: django-admin-sort
Version: 0.4.0
Summary: Sortable changelist, tabular and stacked inlines, drag-and-drop and dropdowns
Home-page: https://github.com/rouxcode/django-admin-sort
Author: Alaric Mägerle
Author-email: info@rouxcode.ch
License: The MIT License
Keywords: django
Platform: OS Independent
Classifier: Environment :: Web Environment
Classifier: Framework :: Django
Classifier: Intended Audience :: Developers
Classifier: License :: OSI Approved :: MIT License
Classifier: Operating System :: OS Independent
Classifier: Programming Language :: Python
Classifier: Topic :: Software Development :: Libraries :: Python Modules
Classifier: Development Status :: 4 - Beta
License-File: LICENCES
Requires-Dist: django (>=2.2)
